{
    "projects": [
        {
            "title": "Teste",
            "img": "",
            "desc": "teste obj 1",
            "tools": [
                "Angular",
                "SASS"
            ]
        },
        {
            "title": "Teste 2",
            "img": "",
            "desc": "teste obj 2",
            "tools": [
                "Java",
                "SQLite"
            ]
        }
    ],
    "languages": [
        {
            "name": "Angular",
            "desc": "angular desc",
            "icon": "",
            "stick": "",
            "link": "https://google.com"
        },
        {
            "name": "Angular",
            "desc": "angular desc",
            "icon": "",
            "stick": "",
            "link": "https://google.com"
        }
    ]
}